urand/__init__.py
urand/cli.py
urand/config.py
urand/config_default.yaml
urand/db.py
urand/study.py
urn_randomization-0.0.1.dist-info/LICENSE
urn_randomization-0.0.1.dist-info/METADATA
urn_randomization-0.0.1.dist-info/WHEEL
urn_randomization-0.0.1.dist-info/entry_points.txt
urn_randomization-0.0.1.dist-info/top_level.txt
urn_randomization-0.0.1.dist-info/RECORD
